app/__init__.py
app/config/__init__.py
noocash_sdk-0.0.11.dist-info/METADATA
noocash_sdk-0.0.11.dist-info/WHEEL
noocash_sdk-0.0.11.dist-info/top_level.txt
noocash_sdk-0.0.11.dist-info/RECORD
