Metadata-Version: 2.1
Name: noocash-sdk
Version: 0.0.11
Summary: Python SDK for mobile money API
Home-page: https://github.com/thepresidentafrica/money-sdks
Author: Mitch Chanza
Author-email: hello@mitch.guru
Classifier: Programming Language :: Python :: 3
Classifier: License :: OSI Approved :: MIT License
Classifier: Operating System :: OS Independent
Requires-Python: >=3.11
